tcgen/__init__.py
tcgen/__main__.py
tcgen/_pattern.py
tcgen/_version.py
tcgen/arena.py
tcgen/generate.py
tcgen/language.py
tcgen/language_test.py
tcgen/parser.py
tcgen/repository.py
tcgen/repository_meta.py
tcgen/utils.py
tcgen/codeforces/__init__.py
tcgen/codeforces/correct_test.py
tcgen/codeforces/explore.py
tcgen/codeforces/inspect.py
tcgen/codeforces/tools.py
tcgen/elements/__init__.py
tcgen/elements/compound.py
tcgen/elements/elements.py
tcgen/elements/integer.py
tcgen/elements/integers.py
tcgen/elements/list.py
tcgen/elements/string.py
tcgen-0.1.2.dist-info/LICENSE
tcgen-0.1.2.dist-info/METADATA
tcgen-0.1.2.dist-info/WHEEL
tcgen-0.1.2.dist-info/top_level.txt
tcgen-0.1.2.dist-info/RECORD
