Metadata-Version: 2.1
Name: tcgen
Version: 0.1.2
Summary: Program synthesis tool. Read a list of strings and create a generator that sample strings from the same distribution as input strings. Focused on test cases of competitive programming problems.
Home-page: https://github.com/mfornet/tcgen
Author: Marcelo Fornet
Author-email: mfornet94@gmail.com
License: MIT
Keywords: program synthesis competitive programming acm icpc codeforces
Platform: UNKNOWN
Classifier: Environment :: Console
Classifier: License :: OSI Approved :: MIT License
Classifier: Programming Language :: Python :: 3.6
